clique/__init__.py
clique/_version.py
clique/collection.py
clique/descriptor.py
clique/error.py
clique/sorted_set.py
clique-1.6.1.dist-info/LICENSE.txt
clique-1.6.1.dist-info/METADATA
clique-1.6.1.dist-info/WHEEL
clique-1.6.1.dist-info/top_level.txt
clique-1.6.1.dist-info/RECORD
