Metadata-Version: 2.1
Name: clique
Version: 1.6.1
Summary: Manage collections with common numerical component
Home-page: https://gitlab.com/4degrees/clique
Author: Martin Pengelly-Phillips
Author-email: martin@4degrees.ltd.uk
License: Apache License (2.0)
Keywords: sequence,pattern,filesystem,collection,numerical
Platform: UNKNOWN
Classifier: License :: OSI Approved :: Apache Software License
Classifier: Intended Audience :: Developers
Classifier: Programming Language :: Python :: 3
Requires-Python: >=2.7, <4.0
Provides-Extra: doc
Provides-Extra: test
Provides-Extra: dev
